{
  "auth": {
    "learningnext8a9b86c1": {
      "service": "Cognito",
      "providerPlugin": "awscloudformation",
      "dependsOn": [],
      "customAuth": false,
      "frontendAuthConfig": {
        "socialProviders": [],
        "usernameAttributes": [],
        "signupAttributes": [
          "EMAIL"
        ],
        "passwordProtectionSettings": {
          "passwordPolicyMinLength": 8,
          "passwordPolicyCharacters": []
        },
        "mfaConfiguration": "OFF",
        "mfaTypes": [
          "SMS"
        ],
        "verificationMechanisms": [
          "EMAIL"
        ]
      }
    }
  },
  "api": {
    "learningnext": {
      "service": "AppSync",
      "providerPlugin": "awscloudformation",
      "output": {
        "authConfig": {
          "defaultAuthentication": {
            "authenticationType": "AMAZON_COGNITO_USER_POOLS",
            "userPoolConfig": {
              "userPoolId": "authlearningnext8a9b86c1"
            }
          },
          "additionalAuthenticationProviders": [
            {
              "authenticationType": "API_KEY",
              "apiKeyConfig": {
                "apiKeyExpirationDays": 7,
                "apiKeyExpirationDate": "2022-04-16T10:12:25.013Z",
                "description": "trial"
              }
            }
          ]
        }
      }
    }
  },
  "storage": {
    "blogImages": {
      "service": "S3",
      "providerPlugin": "awscloudformation",
      "dependsOn": []
    }
  }
}